[
  {
    "sim_time": "2023-02-13 08:01:00",
    "date": "Monday February 13",
    "persona": "Dylan Brooks",
    "about": "Pastor Daniel Brooks",
    "summary": "There is no information provided about Pastor Daniel Brooks or Dylan Brooks's relationship with him. The statements only mention Dylan Brooks's activities and the societal structure, with no reference to Pastor Daniel Brooks."
  },
  {
    "sim_time": "2023-02-13 10:41:30",
    "date": "Monday February 13",
    "persona": "Dylan Brooks",
    "about": "Pastor Daniel Brooks",
    "summary": "Dylan Brooks and Pastor Daniel Brooks have a mentorship-like relationship where Pastor Daniel takes a genuine interest in Dylan's school life, particularly his literature class, and Dylan is open to sharing his thoughts and opinions with Pastor Daniel, indicating a level of trust and respect between them."
  }
]