{
  "persona": {
    "Ethan Walker": {
      "movement": [
        65,
        97
      ],
      "pronunciatio": "\ud83c\udf73\ud83c\udfe0",
      "description": "having breakfast at home @ the Ville:house_1:kitchen:refrigerator",
      "chat": null
    },
    "Jordan Walker": {
      "movement": [
        40,
        86
      ],
      "pronunciatio": "\u23f0\ud83d\udca4",
      "description": "waking up and getting ready (on the way to waking up and getting read) @ the Ville:house_1:bathroom_1:toilet",
      "chat": null
    },
    "Lily Walker": {
      "movement": [
        40,
        86
      ],
      "pronunciatio": "\ud83d\udecb\ufe0f\ud83d\udca4",
      "description": "waking up and getting ready (on the way to waking up and getting read) @ the Ville:house_1:bathroom_1:toilet",
      "chat": null
    },
    "Rodrigo Torres": {
      "movement": [
        100,
        97
      ],
      "pronunciatio": "\ud83c\udf73\ud83c\udfe0",
      "description": "having breakfast at home @ the Ville:house_2:kitchen:refrigerator",
      "chat": null
    },
    "Sofia Torres": {
      "movement": [
        100,
        97
      ],
      "pronunciatio": "\ud83c\udf73\ud83c\udfe0",
      "description": "having breakfast at home @ the Ville:house_2:kitchen:refrigerator",
      "chat": null
    },
    "Harpreet Kaur": {
      "movement": [
        130,
        97
      ],
      "pronunciatio": "\ud83d\udcac",
      "description": "conversing about Harpreet Kaur and Raj Singh conversing about their day ahead at the Government Building, including a meeting for dispute resolution and discussions about civic administration with students like Nadia Kaur @ <persona> Raj Singh",
      "chat": [
        [
          "Harpreet Kaur",
          "Good morning Raj, how's your day starting out?"
        ],
        [
          "Raj Singh",
          "It's starting out well, thanks for asking. I was just thinking about my day ahead at the Government Building. How about you, do you have any plans?"
        ],
        [
          "Harpreet Kaur",
          "I'm heading to the Government Building as well, I have a meeting with some community members to discuss a dispute resolution. Maybe I'll see you there?"
        ],
        [
          "Raj Singh",
          "That sounds like an important meeting, I hope it goes well. I'll be discussing ways to engage with students like Nadia Kaur who are interested in civic administration, maybe our paths will cross during the day."
        ],
        [
          "Harpreet Kaur",
          "That's great, I'm sure Nadia Kaur would appreciate your guidance. I should probably get going soon, but it was nice chatting with you, Raj."
        ]
      ]
    },
    "Raj Singh": {
      "movement": [
        131,
        97
      ],
      "pronunciatio": "\ud83d\udcac",
      "description": "conversing about Harpreet Kaur and Raj Singh conversing about their day ahead at the Government Building, including a meeting for dispute resolution and discussions about civic administration with students like Nadia Kaur @ <persona> Harpreet Kaur",
      "chat": [
        [
          "Harpreet Kaur",
          "Good morning Raj, how's your day starting out?"
        ],
        [
          "Raj Singh",
          "It's starting out well, thanks for asking. I was just thinking about my day ahead at the Government Building. How about you, do you have any plans?"
        ],
        [
          "Harpreet Kaur",
          "I'm heading to the Government Building as well, I have a meeting with some community members to discuss a dispute resolution. Maybe I'll see you there?"
        ],
        [
          "Raj Singh",
          "That sounds like an important meeting, I hope it goes well. I'll be discussing ways to engage with students like Nadia Kaur who are interested in civic administration, maybe our paths will cross during the day."
        ],
        [
          "Harpreet Kaur",
          "That's great, I'm sure Nadia Kaur would appreciate your guidance. I should probably get going soon, but it was nice chatting with you, Raj."
        ]
      ]
    },
    "Nadia Kaur": {
      "movement": [
        112,
        91
      ],
      "pronunciatio": "\ud83d\udecb\ufe0f\ud83d\udca4",
      "description": "waking up and getting ready (on the way to waking up and getting read) @ the Ville:house_3:bathroom_1:toilet",
      "chat": null
    },
    "Dr Linh Nguyen": {
      "movement": [
        178,
        95
      ],
      "pronunciatio": "\ud83c\udf73\ud83c\udfe0",
      "description": "having breakfast at home @ the Ville:house_4:kitchen:refrigerator",
      "chat": null
    },
    "Phoebe Nguyen": {
      "movement": [
        178,
        95
      ],
      "pronunciatio": "\ud83c\udf73\ud83c\udfe0",
      "description": "having breakfast at home @ the Ville:house_4:kitchen:refrigerator",
      "chat": null
    },
    "Julia Nguyen": {
      "movement": [
        153,
        84
      ],
      "pronunciatio": "\u23f0\ud83d\udca4",
      "description": "waking up and getting ready (on the way to waking up and getting read) @ the Ville:house_4:bathroom_1:toilet",
      "chat": null
    },
    "Curtis Bell": {
      "movement": [
        78,
        119
      ],
      "pronunciatio": "\ud83c\udf73\ud83c\udfe0",
      "description": "having breakfast at home @ the Ville:house_5:kitchen:refrigerator",
      "chat": null
    },
    "Patricia Kim": {
      "movement": [
        78,
        119
      ],
      "pronunciatio": "\ud83c\udf73\ud83c\udfe0",
      "description": "having breakfast at home @ the Ville:house_5:kitchen:refrigerator",
      "chat": null
    },
    "Trina Bell": {
      "movement": [
        55,
        109
      ],
      "pronunciatio": "\ud83d\udcac",
      "description": "conversing about Mason Bell and Trina Bell conversing about their daily plans, including Mason's anticipation of seeing his sister Rosie's new art project and Trina's student organizer duties at school @ <persona> Mason Bell",
      "chat": [
        [
          "Trina Bell",
          "Good morning Mason, how are you doing today?"
        ],
        [
          "Mason Bell",
          "Good morning Trina, I'm doing well, thanks. I'm looking forward to seeing Rosie's new art project when it's finished."
        ],
        [
          "Trina Bell",
          "That sounds exciting, I've heard Rosie is really talented. What kind of art project is she working on?"
        ],
        [
          "Mason Bell",
          "She's working on a painting of our neighborhood, and I've heard it's going to be really good. I'm planning to eat breakfast with her before we head out to school, so I'll get to see it then."
        ],
        [
          "Trina Bell",
          "That sounds like a great way to start the day, I'm sure Rosie's painting will be amazing. I have to get going soon, I have my student organizer duties at school today."
        ],
        [
          "Mason Bell",
          "That sounds like a lot of responsibility, what do you have to do for your student organizer duties today?"
        ],
        [
          "Trina Bell",
          "Well, today I have to help organize a meeting for the student council and make sure everything runs smoothly. It's a lot of work, but it's worth it to help make our school a better place."
        ],
        [
          "Mason Bell",
          "That sounds like a big responsibility, I'm sure you'll do a great job. I should probably get going too, I don't want to be late for school and I still need to eat breakfast with Rosie."
        ],
        [
          "Trina Bell",
          "It was nice chatting with you Mason, I'll see you at school later. I should probably get going and have some breakfast before I head out."
        ]
      ]
    },
    "Rosie Bell": {
      "movement": [
        53,
        108
      ],
      "pronunciatio": "\u23f0\ud83d\udca4",
      "description": "waking up and getting ready (on the way to waking up and getting read) @ the Ville:house_5:bathroom_1:toilet",
      "chat": null
    },
    "Mason Bell": {
      "movement": [
        54,
        109
      ],
      "pronunciatio": "\ud83d\udcac",
      "description": "conversing about Mason Bell and Trina Bell conversing about their daily plans, including Mason's anticipation of seeing his sister Rosie's new art project and Trina's student organizer duties at school @ <persona> Trina Bell",
      "chat": [
        [
          "Trina Bell",
          "Good morning Mason, how are you doing today?"
        ],
        [
          "Mason Bell",
          "Good morning Trina, I'm doing well, thanks. I'm looking forward to seeing Rosie's new art project when it's finished."
        ],
        [
          "Trina Bell",
          "That sounds exciting, I've heard Rosie is really talented. What kind of art project is she working on?"
        ],
        [
          "Mason Bell",
          "She's working on a painting of our neighborhood, and I've heard it's going to be really good. I'm planning to eat breakfast with her before we head out to school, so I'll get to see it then."
        ],
        [
          "Trina Bell",
          "That sounds like a great way to start the day, I'm sure Rosie's painting will be amazing. I have to get going soon, I have my student organizer duties at school today."
        ],
        [
          "Mason Bell",
          "That sounds like a lot of responsibility, what do you have to do for your student organizer duties today?"
        ],
        [
          "Trina Bell",
          "Well, today I have to help organize a meeting for the student council and make sure everything runs smoothly. It's a lot of work, but it's worth it to help make our school a better place."
        ],
        [
          "Mason Bell",
          "That sounds like a big responsibility, I'm sure you'll do a great job. I should probably get going too, I don't want to be late for school and I still need to eat breakfast with Rosie."
        ],
        [
          "Trina Bell",
          "It was nice chatting with you Mason, I'll see you at school later. I should probably get going and have some breakfast before I head out."
        ]
      ]
    },
    "Rashad Lewis": {
      "movement": [
        137,
        120
      ],
      "pronunciatio": "\ud83d\udcac",
      "description": "conversing about Rashad Lewis, the coach at the school, and Kendra Hall, the movement instructor at the school, conversing about collaborating on drills to improve students' athletic performance, specifically focusing on teamwork, coordination, and agility, and planning to meet at 5:30 pm to discuss the details @ <persona> Kendra Hall",
      "chat": [
        [
          "Rashad Lewis",
          "Hi Kendra, how's your breakfast going? I'm Rashad, the coach at the school."
        ],
        [
          "Kendra Hall",
          "Hi Rashad, my breakfast is going well, thanks for asking. I'm Kendra, the movement instructor at the school. How's your day starting out?"
        ],
        [
          "Rashad Lewis",
          "It's going well, thanks. I had a good conversation with Parker Lewis yesterday about the upcoming game and I'm looking forward to seeing how the team performs. How about you, do you have any exciting plans for your movement classes today?"
        ],
        [
          "Kendra Hall",
          "That sounds great, Rashad. I'm actually planning a new routine for my movement class today, focusing on teamwork and coordination. I'm excited to see how the students will work together."
        ],
        [
          "Rashad Lewis",
          "That sounds like a great idea, Kendra. Teamwork and coordination are essential skills for any team to succeed. I'm sure your movement class will really benefit from that. Have you considered collaborating with me on some drills that could help improve the students' overall athletic performance?"
        ],
        [
          "Kendra Hall",
          "That's a great idea, Rashad. I'd love to collaborate with you on some drills that can help improve the students' overall athletic performance. Perhaps we can discuss some specific exercises that can help with teamwork and coordination?"
        ],
        [
          "Rashad Lewis",
          "I was thinking we could work on some agility drills that focus on quick changes of direction, as well as some exercises that promote communication and trust among team members. Would you like to meet up after my practice today to discuss some ideas?"
        ],
        [
          "Kendra Hall",
          "That sounds like a great plan, Rashad. I'd love to meet up with you after your practice today to discuss some ideas for the agility drills and teamwork exercises. What time were you thinking?"
        ],
        [
          "Rashad Lewis",
          "How about we meet up at 5:30 pm, right after my practice? We can discuss the details of the drills and exercises then."
        ],
        [
          "Kendra Hall",
          "5:30 pm sounds perfect, Rashad. I'm looking forward to discussing the details of the drills and exercises with you then. Have a great practice and I'll see you later."
        ],
        [
          "Rashad Lewis",
          "Sounds good, Kendra. I'm looking forward to our meeting at 5:30 pm. Have a great day with your movement classes and I'll talk to you later."
        ]
      ]
    },
    "Parker Lewis": {
      "movement": [
        116,
        109
      ],
      "pronunciatio": "\u23f0\ud83d\udca4",
      "description": "waking up and getting ready (on the way to waking up and getting read) @ the Ville:house_6:bathroom_1:toilet",
      "chat": null
    },
    "Kendra Hall": {
      "movement": [
        137,
        120
      ],
      "pronunciatio": "\ud83d\udcac",
      "description": "conversing about Rashad Lewis, the coach at the school, and Kendra Hall, the movement instructor at the school, conversing about collaborating on drills to improve students' athletic performance, specifically focusing on teamwork, coordination, and agility, and planning to meet at 5:30 pm to discuss the details @ <persona> Rashad Lewis",
      "chat": [
        [
          "Rashad Lewis",
          "Hi Kendra, how's your breakfast going? I'm Rashad, the coach at the school."
        ],
        [
          "Kendra Hall",
          "Hi Rashad, my breakfast is going well, thanks for asking. I'm Kendra, the movement instructor at the school. How's your day starting out?"
        ],
        [
          "Rashad Lewis",
          "It's going well, thanks. I had a good conversation with Parker Lewis yesterday about the upcoming game and I'm looking forward to seeing how the team performs. How about you, do you have any exciting plans for your movement classes today?"
        ],
        [
          "Kendra Hall",
          "That sounds great, Rashad. I'm actually planning a new routine for my movement class today, focusing on teamwork and coordination. I'm excited to see how the students will work together."
        ],
        [
          "Rashad Lewis",
          "That sounds like a great idea, Kendra. Teamwork and coordination are essential skills for any team to succeed. I'm sure your movement class will really benefit from that. Have you considered collaborating with me on some drills that could help improve the students' overall athletic performance?"
        ],
        [
          "Kendra Hall",
          "That's a great idea, Rashad. I'd love to collaborate with you on some drills that can help improve the students' overall athletic performance. Perhaps we can discuss some specific exercises that can help with teamwork and coordination?"
        ],
        [
          "Rashad Lewis",
          "I was thinking we could work on some agility drills that focus on quick changes of direction, as well as some exercises that promote communication and trust among team members. Would you like to meet up after my practice today to discuss some ideas?"
        ],
        [
          "Kendra Hall",
          "That sounds like a great plan, Rashad. I'd love to meet up with you after your practice today to discuss some ideas for the agility drills and teamwork exercises. What time were you thinking?"
        ],
        [
          "Rashad Lewis",
          "How about we meet up at 5:30 pm, right after my practice? We can discuss the details of the drills and exercises then."
        ],
        [
          "Kendra Hall",
          "5:30 pm sounds perfect, Rashad. I'm looking forward to discussing the details of the drills and exercises with you then. Have a great practice and I'll see you later."
        ],
        [
          "Rashad Lewis",
          "Sounds good, Kendra. I'm looking forward to our meeting at 5:30 pm. Have a great day with your movement classes and I'll talk to you later."
        ]
      ]
    },
    "Dr Miguel Santos": {
      "movement": [
        136,
        136
      ],
      "pronunciatio": "\ud83d\udcac",
      "description": "conversing about a discussion between Dr. Miguel Santos and Vivian Santos about the new campaign for Town House 1, focusing on improving its public image, highlighting its amenities and services, and exploring potential partnerships with local businesses. @ <persona> Vivian Santos",
      "chat": [
        [
          "Dr Miguel Santos",
          "Good morning Vivian, how's your day starting out?"
        ],
        [
          "Vivian Santos",
          "Good morning Dr. Santos, it's starting out well, thanks. I'm just getting ready for another busy day at the office, trying to finalize the new campaign for Town House 1."
        ],
        [
          "Dr Miguel Santos",
          "That sounds like a challenging project, what's the main focus of the campaign?"
        ],
        [
          "Vivian Santos",
          "The main focus of the campaign is to improve the public image of Town House 1, highlighting its amenities and services to attract more residents and businesses. We're working on creating a new website, social media accounts, and advertising materials to showcase its features and benefits."
        ],
        [
          "Dr Miguel Santos",
          "That sounds like a great initiative, I've heard Town House 1 has a lot of potential for growth and development. What kind of amenities and services are you planning to highlight in the campaign?"
        ],
        [
          "Vivian Santos",
          "We're planning to highlight the newly renovated community center, the state-of-the-art fitness center, and the convenient location with easy access to public transportation. We're also going to emphasize the sense of community and the various events and activities that take place at Town House 1."
        ],
        [
          "Dr Miguel Santos",
          "That's impressive, I've heard great things about the community center and fitness center. How do you plan to measure the success of the campaign and what's the expected timeline for its completion?"
        ],
        [
          "Vivian Santos",
          "We plan to measure the success of the campaign through social media engagement, website traffic, and the number of new residents and businesses that move into Town House 1. As for the timeline, we're expecting to launch the campaign within the next 6-8 weeks, and we'll be monitoring its progress and making adjustments as needed."
        ],
        [
          "Dr Miguel Santos",
          "That's a very ambitious timeline, I wish you the best of luck with the campaign. I'm sure it will have a positive impact on the community. Have you considered reaching out to local businesses to see if they'd be interested in partnering with Town House 1 to offer exclusive discounts or services to residents?"
        ],
        [
          "Vivian Santos",
          "That's a great idea, Dr. Santos, I'll definitely consider reaching out to local businesses to explore potential partnership opportunities. It could be a win-win for both the businesses and the residents of Town House 1."
        ],
        [
          "Dr Miguel Santos",
          "I think partnering with local businesses could be a fantastic way to add value to the community, and I'd be happy to help make some introductions if you'd like. Have you spoken with Ben Carter about the campaign, I'm sure he'd be interested in hearing about the progress?"
        ],
        [
          "Vivian Santos",
          "Thank you, Dr. Santos, I appreciate your offer to help make introductions to local businesses. I have spoken with Ben Carter about the campaign and he's been very supportive of our efforts to improve the public image of Town House 1. I'll definitely keep him updated on our progress and any potential partnerships we may establish with local businesses."
        ],
        [
          "Dr Miguel Santos",
          "I'm glad to hear that Ben Carter is supportive of the campaign, his endorsement will likely carry significant weight in the community. I should probably get going to the pharmacy soon, but it was great catching up with you and hearing about the campaign."
        ]
      ]
    },
    "Vivian Santos": {
      "movement": [
        137,
        136
      ],
      "pronunciatio": "\ud83d\udcac",
      "description": "conversing about a discussion between Dr. Miguel Santos and Vivian Santos about the new campaign for Town House 1, focusing on improving its public image, highlighting its amenities and services, and exploring potential partnerships with local businesses. @ <persona> Dr Miguel Santos",
      "chat": [
        [
          "Dr Miguel Santos",
          "Good morning Vivian, how's your day starting out?"
        ],
        [
          "Vivian Santos",
          "Good morning Dr. Santos, it's starting out well, thanks. I'm just getting ready for another busy day at the office, trying to finalize the new campaign for Town House 1."
        ],
        [
          "Dr Miguel Santos",
          "That sounds like a challenging project, what's the main focus of the campaign?"
        ],
        [
          "Vivian Santos",
          "The main focus of the campaign is to improve the public image of Town House 1, highlighting its amenities and services to attract more residents and businesses. We're working on creating a new website, social media accounts, and advertising materials to showcase its features and benefits."
        ],
        [
          "Dr Miguel Santos",
          "That sounds like a great initiative, I've heard Town House 1 has a lot of potential for growth and development. What kind of amenities and services are you planning to highlight in the campaign?"
        ],
        [
          "Vivian Santos",
          "We're planning to highlight the newly renovated community center, the state-of-the-art fitness center, and the convenient location with easy access to public transportation. We're also going to emphasize the sense of community and the various events and activities that take place at Town House 1."
        ],
        [
          "Dr Miguel Santos",
          "That's impressive, I've heard great things about the community center and fitness center. How do you plan to measure the success of the campaign and what's the expected timeline for its completion?"
        ],
        [
          "Vivian Santos",
          "We plan to measure the success of the campaign through social media engagement, website traffic, and the number of new residents and businesses that move into Town House 1. As for the timeline, we're expecting to launch the campaign within the next 6-8 weeks, and we'll be monitoring its progress and making adjustments as needed."
        ],
        [
          "Dr Miguel Santos",
          "That's a very ambitious timeline, I wish you the best of luck with the campaign. I'm sure it will have a positive impact on the community. Have you considered reaching out to local businesses to see if they'd be interested in partnering with Town House 1 to offer exclusive discounts or services to residents?"
        ],
        [
          "Vivian Santos",
          "That's a great idea, Dr. Santos, I'll definitely consider reaching out to local businesses to explore potential partnership opportunities. It could be a win-win for both the businesses and the residents of Town House 1."
        ],
        [
          "Dr Miguel Santos",
          "I think partnering with local businesses could be a fantastic way to add value to the community, and I'd be happy to help make some introductions if you'd like. Have you spoken with Ben Carter about the campaign, I'm sure he'd be interested in hearing about the progress?"
        ],
        [
          "Vivian Santos",
          "Thank you, Dr. Santos, I appreciate your offer to help make introductions to local businesses. I have spoken with Ben Carter about the campaign and he's been very supportive of our efforts to improve the public image of Town House 1. I'll definitely keep him updated on our progress and any potential partnerships we may establish with local businesses."
        ],
        [
          "Dr Miguel Santos",
          "I'm glad to hear that Ben Carter is supportive of the campaign, his endorsement will likely carry significant weight in the community. I should probably get going to the pharmacy soon, but it was great catching up with you and hearing about the campaign."
        ]
      ]
    },
    "Mateo Santos": {
      "movement": [
        116,
        125
      ],
      "pronunciatio": "\u23f0\ud83d\udca4",
      "description": "waking up and getting ready (on the way to waking up and getting read) @ the Ville:house_7:bathroom_1:toilet",
      "chat": null
    },
    "Gabriel Flores": {
      "movement": [
        178,
        135
      ],
      "pronunciatio": "\ud83c\udf73\ud83c\udfe0",
      "description": "having breakfast at home @ the Ville:house_8:kitchen:refrigerator",
      "chat": null
    },
    "Emilia Flores": {
      "movement": [
        178,
        135
      ],
      "pronunciatio": "\ud83c\udf73\ud83c\udfe0",
      "description": "having breakfast at home @ the Ville:house_8:kitchen:refrigerator",
      "chat": null
    },
    "Noemi Flores": {
      "movement": [
        153,
        124
      ],
      "pronunciatio": "\ud83d\udecb\ufe0f\ud83d\udca4",
      "description": "waking up and getting ready (on the way to waking up and getting read) @ the Ville:house_8:bathroom_1:toilet",
      "chat": null
    },
    "Pastor Daniel Brooks": {
      "movement": [
        138,
        159
      ],
      "pronunciatio": "\ud83c\udf73\ud83c\udfe0",
      "description": "having breakfast at home @ the Ville:house_9:kitchen:refrigerator",
      "chat": null
    },
    "Dylan Brooks": {
      "movement": [
        113,
        148
      ],
      "pronunciatio": "\u23f0\ud83d\udca4",
      "description": "waking up and getting ready (on the way to waking up and getting read) @ the Ville:house_9:bathroom_1:toilet",
      "chat": null
    },
    "Caleb Brooks": {
      "movement": [
        138,
        159
      ],
      "pronunciatio": "\ud83c\udf73\ud83c\udfe0",
      "description": "having breakfast at home @ the Ville:house_9:kitchen:refrigerator",
      "chat": null
    },
    "Professor Emily Carter": {
      "movement": [
        178,
        166
      ],
      "pronunciatio": "\ud83c\udf73\ud83c\udfe0",
      "description": "having breakfast at home @ the Ville:house_10:kitchen:refrigerator",
      "chat": null
    },
    "Ben Carter": {
      "movement": [
        153,
        155
      ],
      "pronunciatio": "\ud83d\udecb\ufe0f\ud83d\udca4",
      "description": "waking up and getting ready (on the way to waking up and getting read) @ the Ville:house_10:bathroom_1:toilet",
      "chat": null
    }
  },
  "meta": {
    "curr_time": "February 13, 2023, 08:18:30"
  }
}